{
  "sections": [
    {
      "name": "Fundamentals of Light and Reflection",
      "description": "This section tests your basic understanding of how light behaves, particularly the laws of reflection and properties of light rays. This knowledge is fundamental to understanding reflection on any surface, plane or curved.",
      "questions": [
        {
          "question": "The bouncing back of light after striking a surface is called:",
          "choices": [
            "Refraction",
            "Dispersion",
            "Reflection",
            "Absorption"
          ],
          "answer": "Reflection"
        },
        {
          "question": "The law of reflection states that the angle of incidence is always ________ the angle of reflection.",
          "choices": [
            "greater than",
            "less than",
            "equal to",
            "unrelated to"
          ],
          "answer": "equal to"
        },
        {
          "question": "The angle of incidence is the angle between the incident ray and the:",
          "choices": [
            "Reflecting surface",
            "Normal",
            "Reflected ray",
            "Tangent"
          ],
          "answer": "Normal"
        },
        {
          "question": "A line drawn perpendicular to the surface at the point of incidence is called the:",
          "choices": [
            "Incident ray",
            "Reflected ray",
            "Tangent",
            "Normal"
          ],
          "answer": "Normal"
        },
        {
          "question": "How does light generally travel in a uniform medium?",
          "choices": [
            "In curved paths",
            "In straight lines",
            "In a zig-zag pattern",
            "In circles"
          ],
          "answer": "In straight lines"
        },
        {
          "question": "Which of the following best describes a beam of light?",
          "choices": [
            "A single photon",
            "A collection of rays",
            "The shadow of an object",
            "The color of an object"
          ],
          "answer": "A collection of rays"
        },
        {
          "question": "An object that gives off its own light is known as:",
          "choices": [
            "A luminous object",
            "A non-luminous object",
            "An opaque object",
            "A transparent object"
          ],
          "answer": "A luminous object"
        },
        {
          "question": "Why can we see a book that does not produce its own light?",
          "choices": [
            "It absorbs all light",
            "It refracts light",
            "It is a source of light",
            "It reflects light from a source into our eyes"
          ],
          "answer": "It reflects light from a source into our eyes"
        },
        {
          "question": "When a beam of light rays traveling parallel to each other strike a surface and remain parallel after reflection, the reflection is:",
          "choices": [
            "Diffuse",
            "Irregular",
            "Specular",
            "Scattered"
          ],
          "answer": "Specular"
        },
        {
          "question": "If a light ray strikes a mirror at an angle of 30° to the normal, what will be the angle of reflection?",
          "choices": [
            "60°",
            "30°",
            "90°",
            "0°"
          ],
          "answer": "30°"
        },
        {
          "question": "Rays of light that meet at a single point are said to be:",
          "choices": [
            "Diverging",
            "Parallel",
            "Converging",
            "Scattering"
          ],
          "answer": "Converging"
        },
        {
          "question": "Rays of light that spread out from a single point are said to be:",
          "choices": [
            "Diverging",
            "Parallel",
            "Converging",
            "Focusing"
          ],
          "answer": "Diverging"
        },
        {
          "question": "The laws of reflection are valid for:",
          "choices": [
            "Plane surfaces only",
            "Curved surfaces only",
            "Both plane and curved surfaces",
            "Only for mirrors, not other surfaces"
          ],
          "answer": "Both plane and curved surfaces"
        },
        {
          "question": "What is the angle of incidence when a ray of light strikes a mirror normally (perpendicularly)?",
          "choices": [
            "90°",
            "45°",
            "180°",
            "0°"
          ],
          "answer": "0°"
        },
        {
          "question": "Which term describes a path along which light energy travels?",
          "choices": [
            "A beam",
            "A wave",
            "A ray",
            "A normal"
          ],
          "answer": "A ray"
        }
      ]
    },
    {
      "name": "Plane Mirrors and Image Formation",
      "description": "This section assesses your knowledge of image formation by plane mirrors. Understanding the characteristics of images formed by plane mirrors is a crucial starting point for comparing them with images formed by curved mirrors.",
      "questions": [
        {
          "question": "The image formed by a plane mirror is always:",
          "choices": [
            "Real and inverted",
            "Virtual and erect",
            "Real and erect",
            "Virtual and inverted"
          ],
          "answer": "Virtual and erect"
        },
        {
          "question": "An image that can be projected onto a screen is called a:",
          "choices": [
            "Virtual image",
            "Phantom image",
            "Real image",
            "Latent image"
          ],
          "answer": "Real image"
        },
        {
          "question": "How does the size of the image in a plane mirror compare to the size of the object?",
          "choices": [
            "The image is larger",
            "The image is smaller",
            "The image is the same size",
            "It depends on the object's distance"
          ],
          "answer": "The image is the same size"
        },
        {
          "question": "If you stand 2 meters in front of a plane mirror, where does your image appear to be?",
          "choices": [
            "2 meters in front of the mirror",
            "4 meters behind the mirror",
            "2 meters behind the mirror",
            "On the surface of the mirror"
          ],
          "answer": "2 meters behind the mirror"
        },
        {
          "question": "The 'left-right' reversal of an image in a plane mirror is known as:",
          "choices": [
            "Upright inversion",
            "Lateral inversion",
            "Total reflection",
            "Magnification"
          ],
          "answer": "Lateral inversion"
        },
        {
          "question": "The focal length of a plane mirror is considered to be:",
          "choices": [
            "Zero",
            "Negative",
            "One",
            "Infinity"
          ],
          "answer": "Infinity"
        },
        {
          "question": "Can a plane mirror be used to focus rays of sunlight to a single point?",
          "choices": [
            "Yes, easily",
            "No, it cannot converge rays",
            "Yes, but only if it's very large",
            "Only if the sun is very close"
          ],
          "answer": "No, it cannot converge rays"
        },
        {
          "question": "What kind of surface does a standard plane mirror have?",
          "choices": [
            "A curved surface",
            "A rough surface",
            "A flat (planar) surface",
            "A spherical surface"
          ],
          "answer": "A flat (planar) surface"
        },
        {
          "question": "If you write the letter 'P' on paper and hold it in front of a plane mirror, how will it appear?",
          "choices": [
            "P",
            "b",
            "d",
            "q"
          ],
          "answer": "q"
        },
        {
          "question": "If you walk towards a plane mirror at a speed of 1 m/s, what is the speed of your image relative to you?",
          "choices": [
            "1 m/s",
            "0.5 m/s",
            "2 m/s",
            "0 m/s"
          ],
          "answer": "2 m/s"
        },
        {
          "question": "A virtual image is formed when reflected light rays:",
          "choices": [
            "Actually intersect",
            "Appear to intersect at a point behind the mirror",
            "Are absorbed by the mirror",
            "Are parallel to each other"
          ],
          "answer": "Appear to intersect at a point behind the mirror"
        },
        {
          "question": "To see your full height in a plane mirror, the minimum height of the mirror must be:",
          "choices": [
            "Equal to your height",
        "Twice your height",
            "Half your height",
            "One-fourth your height"
          ],
          "answer": "Half your height"
        },
        {
          "question": "What is the magnification produced by a plane mirror?",
          "choices": [
            "Greater than 1",
            "Less than 1",
            "Equal to +1",
            "Equal to -1"
          ],
          "answer": "Equal to +1"
        },
        {
          "question": "An image that is 'erect' means it is:",
          "choices": [
            "Upside down",
            "The right way up",
            "Larger than the object",
            "Smaller than the object"
          ],
          "answer": "The right way up"
        },
        {
          "question": "Where are plane mirrors commonly used?",
          "choices": [
            "In car headlights",
            "As magnifying glasses",
            "As looking glasses in bathrooms",
            "In solar cookers"
          ],
          "answer": "As looking glasses in bathrooms"
        }
      ]
    },
    {
      "name": "Basic Geometry and Terminology",
      "description": "This section checks your familiarity with basic geometrical concepts, especially those related to circles and lines. These concepts are directly applied to define the properties of spherical mirrors.",
      "questions": [
        {
          "question": "A spherical mirror is a small part of a large hollow:",
          "choices": [
            "Cube",
            "Cylinder",
            "Sphere",
            "Cone"
          ],
          "answer": "Sphere"
        },
        {
          "question": "A line that is perpendicular to a tangent at the point of contact on a circle is the:",
          "choices": [
            "Chord",
            "Secant",
            "Diameter",
            "Radius"
          ],
          "answer": "Radius"
        },
        {
          "question": "A surface that curves outward, like the back of a spoon, is called:",
          "choices": [
            "Concave",
            "Plane",
            "Convex",
            "Flat"
          ],
          "answer": "Convex"
        },
        {
          "question": "A surface that curves inward, like the inside of a cave or a bowl, is called:",
          "choices": [
            "Concave",
            "Plane",
            "Convex",
            "Bulged"
          ],
          "answer": "Concave"
        },
        {
          "question": "The center of the sphere of which the mirror is a part is called the:",
          "choices": [
            "Pole",
            "Focus",
            "Center of curvature",
            "Apex"
          ],
          "answer": "Center of curvature"
        },
        {
          "question": "What is the relationship between the radius and the diameter of a circle?",
          "choices": [
            "Radius = 2 x Diameter",
            "Diameter = 2 x Radius",
            "Diameter = Radius",
            "Radius = Diameter / 4"
          ],
          "answer": "Diameter = 2 x Radius"
        },
        {
          "question": "A line drawn at a 90° angle to another line is said to be:",
          "choices": [
            "Parallel",
            "Tangent",
            "Skew",
            "Perpendicular"
          ],
          "answer": "Perpendicular"
        },
        {
          "question": "Two lines in a plane that never intersect are called:",
          "choices": [
            "Perpendicular",
            "Parallel",
            "Intersecting",
            "Tangent"
          ],
          "answer": "Parallel"
        },
        {
          "question": "The geometric center of the reflecting surface of a spherical mirror is known as the:",
          "choices": [
            "Center of curvature",
            "Focus",
            "Pole",
            "Axis"
          ],
          "answer": "Pole"
        },
        {
          "question": "A line passing through the pole and the center of curvature of a spherical mirror is called the:",
          "choices": [
            "Normal",
            "Principal Axis",
            "Tangent",
            "Aperture"
          ],
          "answer": "Principal Axis"
        },
        {
          "question": "What is another term for a 'bulged out' surface?",
          "choices": [
            "Concave",
            "Convex",
            "Plane",
            "Depressed"
          ],
          "answer": "Convex"
        },
        {
          "question": "A magnifying glass is a common example of a:",
          "choices": [
            "Concave mirror",
            "Convex mirror",
            "Plane mirror",
            "Convex lens"
          ],
          "answer": "Convex lens"
        },
        {
          "question": "The radius of curvature of a flat, plane surface is:",
          "choices": [
            "Zero",
            "1 meter",
            "Infinity",
            "Negative"
          ],
          "answer": "Infinity"
        },
        {
          "question": "The point where two lines cross each other is called the point of:",
          "choices": [
            "Origin",
            "Intersection",
            "Divergence",
            "Parallelism"
          ],
          "answer": "Intersection"
        },
        {
          "question": "The radius of a sphere is the distance from the ______ to any point on its surface.",
          "choices": [
            "Pole",
            "Edge",
            "Center",
            "Diameter"
          ],
          "answer": "Center"
        }
      ]
    }
  ]
}